{
    "thread_id": "THREAD_004",
    "name": "Thread Name",
    "description": "Thread purpose and goals",
    "start_time": "2025-02-22T11:25:46.640260",
    "status": "completed",
    "objectives": [
        "Objective 1",
        "Objective 2",
        "Objective 3"
    ],
    "required_components": {
        "core_files": [
            "path/to/required/file1.py",
            "path/to/required/file2.py"
        ],
        "config_files": [
            "path/to/config1.json",
            "path/to/config2.json"
        ],
        "test_files": [
            "path/to/test1.py",
            "path/to/test2.py"
        ]
    },
    "verification_steps": [
        {
            "step": "pre_thread_checks",
            "verifications": [
                {
                    "type": "directory_check",
                    "command": "python scripts/verify_thread.py --check-dirs",
                    "expected_result": {
                        "status": "clean",
                        "no_duplicates": true
                    }
                },
                {
                    "type": "environment_check",
                    "command": "python scripts/verify_thread.py --check-env",
                    "expected_result": {
                        "venv_active": true,
                        "pythonpath_valid": true
                    }
                },
                {
                    "type": "test_coverage",
                    "command": "python scripts/verify_thread.py --check-coverage",
                    "expected_result": {
                        "coverage": ">=85%",
                        "tests_passing": true
                    }
                }
            ]
        }
    ],
    "success_criteria": {
        "coverage_requirements": {
            "min_coverage": 85,
            "critical_files": []
        },
        "test_requirements": {
            "unit_tests_passing": true,
            "integration_tests_passing": true
        },
        "isolation_requirements": {
            "no_external_imports": true,
            "workspace_clean": true
        }
    },
    "deliverables": [
        {
            "name": "Component 1",
            "files": [],
            "status": "pending"
        },
        {
            "name": "Tests",
            "files": [],
            "status": "pending"
        }
    ],
    "completion_checklist": [
        "All verification scripts implemented",
        "Test coverage meets 85% minimum",
        "No duplicate directories exist",
        "All tests passing",
        "Documentation updated",
        "Thread state recorded"
    ],
    "error_handling": {
        "max_retries": 3,
        "backup_required": true,
        "recovery_procedures": {
            "directory_conflict": "Run cleanup script and re-verify",
            "test_failure": "Review logs and re-run failing tests",
            "coverage_gap": "Identify uncovered code and add tests"
        }
    },
    "completion_time": "2025-02-23T09:33:45.337899"
}